chiplotle3/__init__.py
chiplotle3/core/__init__.py
chiplotle3/core/errors.py
chiplotle3/core/visitor.py
chiplotle3/core/cfg/__init__.py
chiplotle3/core/cfg/_run_chiplotle.py
chiplotle3/core/cfg/_run_chiplotle_virtual.py
chiplotle3/core/cfg/cfg.py
chiplotle3/core/cfg/get_config_value.py
chiplotle3/core/cfg/initialize_files.py
chiplotle3/core/cfg/read_config_file.py
chiplotle3/core/cfg/write_config_file.py
chiplotle3/core/cfg/write_log_file.py
chiplotle3/core/imports/__init__.py
chiplotle3/core/imports/get_functions_in_module.py
chiplotle3/core/imports/package_import.py
chiplotle3/core/imports/remove_modules_from_namespace.py
chiplotle3/core/interfaces/__init__.py
chiplotle3/core/interfaces/formatdecorator.py
chiplotle3/core/interfaces/interface.py
chiplotle3/core/interfaces/margins/__init__.py
chiplotle3/core/interfaces/margins/interface.py
chiplotle3/core/interfaces/parentage/__init__.py
chiplotle3/core/interfaces/parentage/interface.py
chiplotle3/examples/__init__.py
chiplotle3/examples/abstract_masterpiece.py
chiplotle3/examples/abstract_masterpiece_file.py
chiplotle3/examples/abstract_masterpiece_virtual.py
chiplotle3/examples/importing_an_hpgl_file.py
chiplotle3/examples/liveplot_data-to-path.py
chiplotle3/examples/liveplot_virtual_generic.py
chiplotle3/examples/liveplot_virtual_specific.py
chiplotle3/fonts/__init__.py
chiplotle3/fonts/dorkbot.py
chiplotle3/geometry/__init__.py
chiplotle3/geometry/core/__init__.py
chiplotle3/geometry/core/affixformatvisitor.py
chiplotle3/geometry/core/coordinate.py
chiplotle3/geometry/core/coordinatearray.py
chiplotle3/geometry/core/coordinatearraypropertiesmixin.py
chiplotle3/geometry/core/group.py
chiplotle3/geometry/core/hpglformatvisitor.py
chiplotle3/geometry/core/label.py
chiplotle3/geometry/core/layer.py
chiplotle3/geometry/core/layersvisitor.py
chiplotle3/geometry/core/metadata.py
chiplotle3/geometry/core/path.py
chiplotle3/geometry/core/polygon.py
chiplotle3/geometry/core/shape.py
chiplotle3-0.4.5.dist-info/LICENSE
chiplotle3-0.4.5.dist-info/METADATA
chiplotle3-0.4.5.dist-info/WHEEL
chiplotle3-0.4.5.dist-info/entry_points.txt
chiplotle3-0.4.5.dist-info/top_level.txt
chiplotle3-0.4.5.dist-info/RECORD
