Metadata-Version: 2.2
Name: Chiplotle3
Version: 0.4.5
Summary: Chiplotle is an HPGL Python API.
Home-page: http://music.columbia.edu/cmc/chiplotle
Author: Víctor Adán and Douglas Repetto
Author-email: chiplotle@music.columbia.edu
Classifier: Programming Language :: Python :: 3
Classifier: License :: OSI Approved :: GNU General Public License v3 (GPLv3)
Classifier: Operating System :: OS Independent
Requires-Python: >=3.6
License-File: LICENSE
Requires-Dist: pyserial
Requires-Dist: numpy
Requires-Dist: apply
Requires-Dist: future
